AUTHORS
COPYING
COPYING.LESSER
MANIFEST.in
README.rst
setup.py
pystrix/__init__.py
pystrix.egg-info/PKG-INFO
pystrix.egg-info/SOURCES.txt
pystrix.egg-info/dependency_links.txt
pystrix.egg-info/top_level.txt
pystrix/agi/__init__.py
pystrix/agi/agi.py
pystrix/agi/agi_core.py
pystrix/agi/core.py
pystrix/agi/fastagi.py
pystrix/ami/__init__.py
pystrix/ami/ami.py
pystrix/ami/app_confbridge.py
pystrix/ami/app_confbridge_events.py
pystrix/ami/app_meetme.py
pystrix/ami/app_meetme_events.py
pystrix/ami/core.py
pystrix/ami/core_events.py
pystrix/ami/dahdi.py
pystrix/ami/dahdi_events.py
pystrix/ami/generic_transforms.py