Metadata-Version: 2.1
Name: pystrix
Version: 1.2.0
Summary: Python bindings for Asterisk Manager Interface and Asterisk Gateway Interface
Home-page: https://github.com/IVRTech/pystrix
Author: Marta Solano
Author-email: marta.solano@ivrtechnology.com
License: GNU General Public License
Platform: OS Independent
Classifier: Intended Audience :: Developers
Classifier: License :: OSI Approved :: GNU General Public License v3 or later (GPLv3+)
Classifier: Operating System :: OS Independent
Classifier: Programming Language :: Python
Classifier: Programming Language :: Python :: 2
Classifier: Programming Language :: Python :: 2.7
Classifier: Programming Language :: Python :: 3
Classifier: Programming Language :: Python :: 3.4
Classifier: Programming Language :: Python :: 3.5
Classifier: Programming Language :: Python :: 3.6
Classifier: Topic :: Communications :: Telephony
License-File: COPYING
License-File: COPYING.LESSER
License-File: AUTHORS
